flag/__init__.py
flag/error.py
flag/flag.py
flag/fmt.py
flag/panic.py
flag/pointer.py
flag/strconv.py
flag/time.py
flag/zero.py
go_flag-2.0.1.dist-info/LICENSE
go_flag-2.0.1.dist-info/METADATA
go_flag-2.0.1.dist-info/WHEEL
go_flag-2.0.1.dist-info/top_level.txt
go_flag-2.0.1.dist-info/RECORD
