Metadata-Version: 2.1
Name: go-flag
Version: 2.0.1
Summary: A port of Go's flag package to Python
Author-email: Josh Holbrook <josh.holbrook@gmail.com>
License: BSD-3
Project-URL: Repository, https://github.com/jfhbrook/go-flag
Keywords: go,golang,flag,options,cli
Classifier: Programming Language :: Python
Classifier: Development Status :: 4 - Beta
Classifier: Intended Audience :: Developers
Classifier: License :: OSI Approved :: MIT License
Classifier: Operating System :: OS Independent
Classifier: Programming Language :: Go
Classifier: Programming Language :: Python
Classifier: Programming Language :: Python :: 3
Classifier: Programming Language :: Python :: 3.12
Classifier: Programming Language :: Python :: 3.13
Classifier: Topic :: Software Development :: Libraries
Requires-Python: >=3.12
License-File: LICENSE
Provides-Extra: dev
Requires-Dist: flake8; extra == "dev"
Requires-Dist: flake8-black; extra == "dev"
Requires-Dist: pytest; extra == "dev"
Requires-Dist: black; extra == "dev"
Requires-Dist: isort; extra == "dev"
Requires-Dist: jupyter-console; extra == "dev"
Requires-Dist: mkdocs; extra == "dev"
Requires-Dist: mkdocs-bootstrap386; extra == "dev"
Requires-Dist: mkdocstrings[python]; extra == "dev"
Requires-Dist: toml; extra == "dev"
Requires-Dist: validate-pyproject[all]; extra == "dev"
